[
  {
    "name": "Senior Database Administrator (DBA) Evident Change Remote (US) - $93K - $103K Information Technology Health &amp; Well-Being Education Human Rights &amp; Equality Evident Change is a nonprofit that uses data and research to improve our social systems. Posted 4 days ago",
    "company_name": "Tech Jobs For Good",
    "location": "Unknown",
    "remote": "Remote",
    "location_lat": 26.4925331,
    "location_lon": 92.3308789,
    "description": "",
    "type": "Unknown",
    "source": "TechJobsForGood",
    "source_url": "https://www.techjobsforgood.com/jobs/33274/?ref=homepage",
    "posted": "2026-05-26T03:38:01.248Z",
    "impact_number": 0,
    "audit_number": 0,
    "audit_text": "",
    "tags": [
      "TechJobsForGood",
      "Mission Driven",
      "Tech"
    ],
    "ai_summary": "",
    "ai_red_flag_summary": "",
    "ai_score": 0,
    "ai_red_flag_score": 0,
    "ai_impact_summary": "",
    "ai_impact_score": 0
  },
  {
    "name": "Director, Product Growth &amp; Partnerships NAF Remote (US) - $122K Product Education Economic Development NAF solves some of the biggest challenges facing education and the economy by bringing education, business, and community leaders together to transform the high school experience. Posted 3 days ago",
    "company_name": "Tech Jobs For Good",
    "location": "Unknown",
    "remote": "Remote",
    "location_lat": 26.4925331,
    "location_lon": 92.3308789,
    "description": "",
    "type": "Unknown",
    "source": "TechJobsForGood",
    "source_url": "https://www.techjobsforgood.com/jobs/33268/?ref=homepage",
    "posted": "2026-05-26T03:38:01.248Z",
    "impact_number": 0,
    "audit_number": 0,
    "audit_text": "",
    "tags": [
      "TechJobsForGood",
      "Mission Driven",
      "Tech"
    ],
    "ai_summary": "",
    "ai_red_flag_summary": "",
    "ai_score": 0,
    "ai_red_flag_score": 0,
    "ai_impact_summary": "",
    "ai_impact_score": 0
  },
  {
    "name": "Staff Software Engineer Art of Problem Solving San Diego, CA (Hybrid) - $190K - $210K Software Engineering Education Art of Problem Solving (AoPS) is on a mission to discover, inspire, and train the great problem solvers of the next generation. Since 2003, we have trained hundreds of thousands of the country’s top students, through our online school, in-person academies, textbooks, and online learning systems. Posted 4 days ago",
    "company_name": "Tech Jobs For Good",
    "location": "San Diego, CA",
    "remote": "Unknown",
    "location_lat": 32.7174202,
    "location_lon": -117.162772,
    "description": "",
    "type": "Unknown",
    "source": "TechJobsForGood",
    "source_url": "https://www.techjobsforgood.com/jobs/33256/?ref=homepage",
    "posted": "2026-05-26T03:38:01.248Z",
    "impact_number": 0,
    "audit_number": 0,
    "audit_text": "",
    "tags": [
      "TechJobsForGood",
      "Mission Driven",
      "Tech"
    ],
    "ai_summary": "",
    "ai_red_flag_summary": "",
    "ai_score": 0,
    "ai_red_flag_score": 0,
    "ai_impact_summary": "",
    "ai_impact_score": 0
  },
  {
    "name": "Data and Research Analyst State Power Fund Remote (US) - $70K - $90K Data + Analytics Human Rights &amp; Equality Partners &amp; Advocates Public Service &amp; Civic Engagement State Power Fund is devoted to measuring and amplifying the power of state-based grassroots organizing groups. We work with partner organizations across the country to create and standardize measurements of grassroots power at the state and local levels by developing the analytics skills of their data managers, facilitating academic research partnerships, and pursuing independent research projects. Posted 3 days ago",
    "company_name": "Tech Jobs For Good",
    "location": "Unknown",
    "remote": "Remote",
    "location_lat": 26.4925331,
    "location_lon": 92.3308789,
    "description": "",
    "type": "Unknown",
    "source": "TechJobsForGood",
    "source_url": "https://www.techjobsforgood.com/jobs/33213/?ref=homepage",
    "posted": "2026-05-26T03:38:01.248Z",
    "impact_number": 0,
    "audit_number": 0,
    "audit_text": "",
    "tags": [
      "TechJobsForGood",
      "Mission Driven",
      "Tech"
    ],
    "ai_summary": "",
    "ai_red_flag_summary": "",
    "ai_score": 0,
    "ai_red_flag_score": 0,
    "ai_impact_summary": "",
    "ai_impact_score": 0
  },
  {
    "name": "Senior Software Engineer UPchieve Remote (US) - $155K - $184K Software Engineering Education UPchieve is an ed-tech nonprofit that connects low-income HS students with live tutors any time they need it. Posted 3 weeks ago",
    "company_name": "Tech Jobs For Good",
    "location": "Unknown",
    "remote": "Remote",
    "location_lat": 26.4925331,
    "location_lon": 92.3308789,
    "description": "",
    "type": "Unknown",
    "source": "TechJobsForGood",
    "source_url": "https://www.techjobsforgood.com/jobs/32939/?ref=homepage",
    "posted": "2026-05-26T03:38:01.248Z",
    "impact_number": 0,
    "audit_number": 0,
    "audit_text": "",
    "tags": [
      "TechJobsForGood",
      "Mission Driven",
      "Tech"
    ],
    "ai_summary": "",
    "ai_red_flag_summary": "",
    "ai_score": 0,
    "ai_red_flag_score": 0,
    "ai_impact_summary": "",
    "ai_impact_score": 0
  },
  {
    "name": "Junior DevOps Engineer Patrick J. McGovern Foundation Remote (US) - $70K - $106K Software Engineering Partners &amp; Advocates Public Infrastructure We are tech-inspired global changemakers, optimists, and visionaries advancing AI and data solutions to create a thriving, equitable, and sustainable future for all. Posted 2 weeks ago",
    "company_name": "Tech Jobs For Good",
    "location": "Unknown",
    "remote": "Remote",
    "location_lat": 26.4925331,
    "location_lon": 92.3308789,
    "description": "",
    "type": "Unknown",
    "source": "TechJobsForGood",
    "source_url": "https://www.techjobsforgood.com/jobs/33096/?ref=homepage",
    "posted": "2026-05-26T03:38:01.248Z",
    "impact_number": 0,
    "audit_number": 0,
    "audit_text": "",
    "tags": [
      "TechJobsForGood",
      "Mission Driven",
      "Tech"
    ],
    "ai_summary": "",
    "ai_red_flag_summary": "",
    "ai_score": 0,
    "ai_red_flag_score": 0,
    "ai_impact_summary": "",
    "ai_impact_score": 0
  },
  {
    "name": "Senior Product Manager Project Basta Remote (NY, NJ, MA, CT, PA, FL) (New York, NY preferred) - $150K - $189K Product Education Economic Development To create a bridge of opportunity between employers and first-generation college goers of color to increase knowledge workforce diversity at all levels. Posted 1 week ago",
    "company_name": "Tech Jobs For Good",
    "location": "NY, NJ",
    "remote": "Remote",
    "location_lat": 37.3708,
    "location_lon": -122.0375,
    "description": "",
    "type": "Unknown",
    "source": "TechJobsForGood",
    "source_url": "https://www.techjobsforgood.com/jobs/33178/?ref=homepage",
    "posted": "2026-05-26T03:38:01.248Z",
    "impact_number": 0,
    "audit_number": 0,
    "audit_text": "",
    "tags": [
      "TechJobsForGood",
      "Mission Driven",
      "Tech"
    ],
    "ai_summary": "",
    "ai_red_flag_summary": "",
    "ai_score": 0,
    "ai_red_flag_score": 0,
    "ai_impact_summary": "",
    "ai_impact_score": 0
  },
  {
    "name": "Junior Engineer, AI BME Strategies Remote (US) - $71K - $83K Software Engineering Health &amp; Well-Being Partners &amp; Advocates Public Service &amp; Civic Engagement BME Strategies is a specialty Public Health consulting firm with over two decades experience driving sustainable change rooted in community health and equity. Posted 3 weeks ago",
    "company_name": "Tech Jobs For Good",
    "location": "Junior Engineer, AI",
    "remote": "Remote",
    "location_lat": 0,
    "location_lon": 0,
    "description": "",
    "type": "Unknown",
    "source": "TechJobsForGood",
    "source_url": "https://www.techjobsforgood.com/jobs/32953/?ref=homepage",
    "posted": "2026-05-26T03:38:02.983Z",
    "impact_number": 0,
    "audit_number": 0,
    "audit_text": "",
    "tags": [
      "TechJobsForGood",
      "Mission Driven",
      "Tech"
    ],
    "ai_summary": "",
    "ai_red_flag_summary": "",
    "ai_score": 0,
    "ai_red_flag_score": 0,
    "ai_impact_summary": "",
    "ai_impact_score": 0
  },
  {
    "name": "Implementation Engineer Recidiviz New York, NY/Oakland, CA/Remote (US) - $97K Software Engineering Human Rights &amp; Equality Recidiviz is a non-profit technology company based in San Francisco, CA. We build common, open source technical infrastructure to help the criminal justice system end mass incarceration and focus on ongoing iteration towards better outcomes (both for the public and the individuals in the system). Posted 3 weeks ago",
    "company_name": "Tech Jobs For Good",
    "location": "New York, NY",
    "remote": "Remote",
    "location_lat": 40.7128,
    "location_lon": -74.006,
    "description": "",
    "type": "Unknown",
    "source": "TechJobsForGood",
    "source_url": "https://www.techjobsforgood.com/jobs/32771/?ref=homepage",
    "posted": "2026-05-26T03:38:01.248Z",
    "impact_number": 0,
    "audit_number": 0,
    "audit_text": "",
    "tags": [
      "TechJobsForGood",
      "Mission Driven",
      "Tech"
    ],
    "ai_summary": "",
    "ai_red_flag_summary": "",
    "ai_score": 0,
    "ai_red_flag_score": 0,
    "ai_impact_summary": "",
    "ai_impact_score": 0
  },
  {
    "name": "Director of Data Strategy Project Basta Remote (NY, NJ, MA, CT, PA, FL) (New York, NY preferred) - $130K - $163K Data + Analytics Education Economic Development To create a bridge of opportunity between employers and first-generation college goers of color to increase knowledge workforce diversity at all levels. Posted 1 week ago",
    "company_name": "Tech Jobs For Good",
    "location": "NY, NJ",
    "remote": "Remote",
    "location_lat": 37.3708,
    "location_lon": -122.0375,
    "description": "",
    "type": "Unknown",
    "source": "TechJobsForGood",
    "source_url": "https://www.techjobsforgood.com/jobs/33177/?ref=homepage",
    "posted": "2026-05-26T03:38:01.248Z",
    "impact_number": 0,
    "audit_number": 0,
    "audit_text": "",
    "tags": [
      "TechJobsForGood",
      "Mission Driven",
      "Tech"
    ],
    "ai_summary": "",
    "ai_red_flag_summary": "",
    "ai_score": 0,
    "ai_red_flag_score": 0,
    "ai_impact_summary": "",
    "ai_impact_score": 0
  },
  {
    "name": "Senior Data Scientist Element14 Washington, DC (Hybrid) / Remote (US) - $160K - $200K Data + Analytics Economic Development Public Service &amp; Civic Engagement Partners &amp; Advocates Element14 is a public sector consulting firm helping federal and state agencies put product, data, and engineering to work in service of the mission. We are small, senior, and deliberately so - a place to work on hard problems alongside leaders who have sat on both sides of the table. Posted 2 weeks ago",
    "company_name": "Tech Jobs For Good",
    "location": "Washington, DC",
    "remote": "Remote",
    "location_lat": 38.8950982,
    "location_lon": -77.0363849,
    "description": "",
    "type": "Unknown",
    "source": "TechJobsForGood",
    "source_url": "https://www.techjobsforgood.com/jobs/33030/?ref=homepage",
    "posted": "2026-05-26T03:38:01.248Z",
    "impact_number": 0,
    "audit_number": 0,
    "audit_text": "",
    "tags": [
      "TechJobsForGood",
      "Mission Driven",
      "Tech"
    ],
    "ai_summary": "",
    "ai_red_flag_summary": "",
    "ai_score": 0,
    "ai_red_flag_score": 0,
    "ai_impact_summary": "",
    "ai_impact_score": 0
  },
  {
    "name": "Member of Technical Staff CivAI Berkeley, CA (Hybrid) - $125K - $200K Software Engineering Partners &amp; Advocates Global Peace &amp; Safety Preparing state and local governments for AI security risksPreparing state and local governments for AI security risks using live software demonstrations. Posted 1 week ago",
    "company_name": "Tech Jobs For Good",
    "location": "Berkeley, CA",
    "remote": "Unknown",
    "location_lat": 37.8716,
    "location_lon": -122.2727,
    "description": "",
    "type": "Unknown",
    "source": "TechJobsForGood",
    "source_url": "https://www.techjobsforgood.com/jobs/33185/?ref=homepage",
    "posted": "2026-05-26T03:38:01.248Z",
    "impact_number": 0,
    "audit_number": 0,
    "audit_text": "",
    "tags": [
      "TechJobsForGood",
      "Mission Driven",
      "Tech"
    ],
    "ai_summary": "",
    "ai_red_flag_summary": "",
    "ai_score": 0,
    "ai_red_flag_score": 0,
    "ai_impact_summary": "",
    "ai_impact_score": 0
  },
  {
    "name": "Data Analyst Main Library Alliance Cedar Knolls, NJ (Hybrid) - $70K - $80K Data + Analytics Main Library Alliance is a public library network that provides quality services and technology frameworks to support its member libraries in Essex, Hunterdon, Morris, Somerset, Union, and Warren Counties. Posted 4 weeks ago",
    "company_name": "Tech Jobs For Good",
    "location": "Cedar Knolls, NJ",
    "remote": "Unknown",
    "location_lat": 30.5,
    "location_lon": -97.9,
    "description": "",
    "type": "Unknown",
    "source": "TechJobsForGood",
    "source_url": "https://www.techjobsforgood.com/jobs/32686/?ref=homepage",
    "posted": "2026-05-26T03:38:01.248Z",
    "impact_number": 0,
    "audit_number": 0,
    "audit_text": "",
    "tags": [
      "TechJobsForGood",
      "Mission Driven",
      "Tech"
    ],
    "ai_summary": "",
    "ai_red_flag_summary": "",
    "ai_score": 0,
    "ai_red_flag_score": 0,
    "ai_impact_summary": "",
    "ai_impact_score": 0
  },
  {
    "name": "Data Analyst: Create Datasets, Support Investigations (6444) Office of the New York State Attorney General New York, NY - $93K Data + Analytics Public Service &amp; Civic Engagement Public Infrastructure As head of the Department of Law, the Attorney General is both the People&#39;s Lawyer and the state&#39;s chief legal officer. The Attorney General serves as the guardian of the legal rights of the people of New York, its organizations, and its natural resources. Posted 3 weeks ago",
    "company_name": "Tech Jobs For Good",
    "location": "Unknown",
    "remote": "Unknown",
    "location_lat": 26.4925331,
    "location_lon": 92.3308789,
    "description": "",
    "type": "Unknown",
    "source": "TechJobsForGood",
    "source_url": "https://www.techjobsforgood.com/jobs/32963/?ref=homepage",
    "posted": "2026-05-26T03:38:01.248Z",
    "impact_number": 0,
    "audit_number": 0,
    "audit_text": "",
    "tags": [
      "TechJobsForGood",
      "Mission Driven",
      "Tech"
    ],
    "ai_summary": "",
    "ai_red_flag_summary": "",
    "ai_score": 0,
    "ai_red_flag_score": 0,
    "ai_impact_summary": "",
    "ai_impact_score": 0
  },
  {
    "name": "Software Engineer IV - Full Stack Mighty Acorn Remote (US) - $130K - $150K Software Engineering Partners &amp; Advocates Education Public Infrastructure Public Service &amp; Civic Engagement At Mighty Acorn, we make it easier for governments to deliver world-class digital services. From renewing a fishing license to applying for unemployment benefits, we build digital services that enhance public trust and satisfaction. Posted 3 weeks ago",
    "company_name": "Tech Jobs For Good",
    "location": "Unknown",
    "remote": "Remote",
    "location_lat": 26.4925331,
    "location_lon": 92.3308789,
    "description": "",
    "type": "Unknown",
    "source": "TechJobsForGood",
    "source_url": "https://www.techjobsforgood.com/jobs/32892/?ref=homepage",
    "posted": "2026-05-26T03:38:01.248Z",
    "impact_number": 0,
    "audit_number": 0,
    "audit_text": "",
    "tags": [
      "TechJobsForGood",
      "Mission Driven",
      "Tech"
    ],
    "ai_summary": "",
    "ai_red_flag_summary": "",
    "ai_score": 0,
    "ai_red_flag_score": 0,
    "ai_impact_summary": "",
    "ai_impact_score": 0
  },
  {
    "name": "Senior Engineer - Data, Platform &amp; Analytics Element14 Washington, DC (Hybrid) / Remote (US) - $140K - $180K Data + Analytics Economic Development Public Service &amp; Civic Engagement Partners &amp; Advocates Element14 is a public sector consulting firm helping federal and state agencies put product, data, and engineering to work in service of the mission. We are small, senior, and deliberately so - a place to work on hard problems alongside leaders who have sat on both sides of the table. Posted 2 weeks ago",
    "company_name": "Tech Jobs For Good",
    "location": "Washington, DC",
    "remote": "Remote",
    "location_lat": 38.8950982,
    "location_lon": -77.0363849,
    "description": "",
    "type": "Unknown",
    "source": "TechJobsForGood",
    "source_url": "https://www.techjobsforgood.com/jobs/33032/?ref=homepage",
    "posted": "2026-05-26T03:38:01.248Z",
    "impact_number": 0,
    "audit_number": 0,
    "audit_text": "",
    "tags": [
      "TechJobsForGood",
      "Mission Driven",
      "Tech"
    ],
    "ai_summary": "",
    "ai_red_flag_summary": "",
    "ai_score": 0,
    "ai_red_flag_score": 0,
    "ai_impact_summary": "",
    "ai_impact_score": 0
  },
  {
    "name": "Product Designer CivAI Berkeley, CA (Hybrid) - $125K - $150K Design + UX Partners &amp; Advocates Global Peace &amp; Safety Preparing state and local governments for AI security risksPreparing state and local governments for AI security risks using live software demonstrations. Posted 1 week ago",
    "company_name": "Tech Jobs For Good",
    "location": "Berkeley, CA",
    "remote": "Unknown",
    "location_lat": 37.8716,
    "location_lon": -122.2727,
    "description": "",
    "type": "Unknown",
    "source": "TechJobsForGood",
    "source_url": "https://www.techjobsforgood.com/jobs/33184/?ref=homepage",
    "posted": "2026-05-26T03:38:01.248Z",
    "impact_number": 0,
    "audit_number": 0,
    "audit_text": "",
    "tags": [
      "TechJobsForGood",
      "Mission Driven",
      "Tech"
    ],
    "ai_summary": "",
    "ai_red_flag_summary": "",
    "ai_score": 0,
    "ai_red_flag_score": 0,
    "ai_impact_summary": "",
    "ai_impact_score": 0
  },
  {
    "name": "Senior AI / Full-Stack Engineer Element14 Washington, DC (Hybrid) / Remote (US) - $160K - $200K Software Engineering Economic Development Public Service &amp; Civic Engagement Partners &amp; Advocates Element14 is a public sector consulting firm helping federal and state agencies put product, data, and engineering to work in service of the mission. We are small, senior, and deliberately so - a place to work on hard problems alongside leaders who have sat on both sides of the table. Posted 2 weeks ago",
    "company_name": "Tech Jobs For Good",
    "location": "Washington, DC",
    "remote": "Remote",
    "location_lat": 38.8950982,
    "location_lon": -77.0363849,
    "description": "",
    "type": "Unknown",
    "source": "TechJobsForGood",
    "source_url": "https://www.techjobsforgood.com/jobs/33031/?ref=homepage",
    "posted": "2026-05-26T03:38:01.248Z",
    "impact_number": 0,
    "audit_number": 0,
    "audit_text": "",
    "tags": [
      "TechJobsForGood",
      "Mission Driven",
      "Tech"
    ],
    "ai_summary": "",
    "ai_red_flag_summary": "",
    "ai_score": 0,
    "ai_red_flag_score": 0,
    "ai_impact_summary": "",
    "ai_impact_score": 0
  },
  {
    "name": "Analytics Engineer II Oregon State University Foundation Corvallis, OR - $90K Data + Analytics Education Partners &amp; Advocates We partner with Oregon State University to engage our community, inspire investment, and steward resources to enhance the university’s excellence and impact. Posted 5 days ago",
    "company_name": "Tech Jobs For Good",
    "location": "Corvallis, OR",
    "remote": "Unknown",
    "location_lat": 44.5645659,
    "location_lon": -123.2620435,
    "description": "",
    "type": "Unknown",
    "source": "TechJobsForGood",
    "source_url": "https://www.techjobsforgood.com/jobs/33212/?ref=homepage",
    "posted": "2026-05-26T03:38:01.248Z",
    "impact_number": 0,
    "audit_number": 0,
    "audit_text": "",
    "tags": [
      "TechJobsForGood",
      "Mission Driven",
      "Tech"
    ],
    "ai_summary": "",
    "ai_red_flag_summary": "",
    "ai_score": 0,
    "ai_red_flag_score": 0,
    "ai_impact_summary": "",
    "ai_impact_score": 0
  },
  {
    "name": "Project Manager, Marketing &amp; Communications at Re:wild Re:wild Remote (US) - $75K - $90K Digital Marketing Re:wild is a nonprofit organization dedicated to conservation and wildlife protection. Posted 3 weeks ago",
    "company_name": "Tech Jobs For Good",
    "location": "Unknown",
    "remote": "Remote",
    "location_lat": 26.4925331,
    "location_lon": 92.3308789,
    "description": "",
    "type": "Unknown",
    "source": "TechJobsForGood",
    "source_url": "https://www.techjobsforgood.com/jobs/32789/?ref=homepage",
    "posted": "2026-05-26T03:38:01.248Z",
    "impact_number": 0,
    "audit_number": 0,
    "audit_text": "",
    "tags": [
      "TechJobsForGood",
      "Mission Driven",
      "Tech"
    ],
    "ai_summary": "",
    "ai_red_flag_summary": "",
    "ai_score": 0,
    "ai_red_flag_score": 0,
    "ai_impact_summary": "",
    "ai_impact_score": 0
  },
  {
    "name": "Machine Learning Scientist Blue Rose Research Remote (US) / New York, NY (Hybrid) - $140K - $190K Software Engineering Public Service &amp; Civic Engagement Partners &amp; Advocates We’re a team of 30+ passionate and progressive software engineers, machine learning engineers, and social scientists on a mission to make high quality research and testing widely available for the progressive community. Posted 3 weeks ago",
    "company_name": "Tech Jobs For Good",
    "location": "New York, NY",
    "remote": "Remote",
    "location_lat": 40.7128,
    "location_lon": -74.006,
    "description": "",
    "type": "Unknown",
    "source": "TechJobsForGood",
    "source_url": "https://www.techjobsforgood.com/jobs/32902/?ref=homepage",
    "posted": "2026-05-26T03:38:01.248Z",
    "impact_number": 0,
    "audit_number": 0,
    "audit_text": "",
    "tags": [
      "TechJobsForGood",
      "Mission Driven",
      "Tech"
    ],
    "ai_summary": "",
    "ai_red_flag_summary": "",
    "ai_score": 0,
    "ai_red_flag_score": 0,
    "ai_impact_summary": "",
    "ai_impact_score": 0
  },
  {
    "name": "Senior Software Engineer (IoT) Swiftly Remote (US / Ontario / British Columbia) - $140K - $205K Software Engineering Human Rights &amp; Equality Public Infrastructure Climate Change Swiftly is the leading transit data platform for agencies to share real-time passenger information, manage day-to-day operations, and improve service performance. Posted 4 weeks ago",
    "company_name": "Tech Jobs For Good",
    "location": "Unknown",
    "remote": "Remote",
    "location_lat": 26.4925331,
    "location_lon": 92.3308789,
    "description": "",
    "type": "Unknown",
    "source": "TechJobsForGood",
    "source_url": "https://www.techjobsforgood.com/jobs/32706/?ref=homepage",
    "posted": "2026-05-26T03:38:01.248Z",
    "impact_number": 0,
    "audit_number": 0,
    "audit_text": "",
    "tags": [
      "TechJobsForGood",
      "Mission Driven",
      "Tech"
    ],
    "ai_summary": "",
    "ai_red_flag_summary": "",
    "ai_score": 0,
    "ai_red_flag_score": 0,
    "ai_impact_summary": "",
    "ai_impact_score": 0
  },
  {
    "name": "Product Manager - Data Services at Ekotrope Ekotrope Boston, MA/Remote (US) - $120K - $150K Product Clean Energy Ekotrope was founded in 2011 with the mission to empower people with technology and insights to drive informed decisions that move our built environment towards sustainability. Posted 3 weeks ago",
    "company_name": "Tech Jobs For Good",
    "location": "Boston, MA",
    "remote": "Remote",
    "location_lat": 42.3601,
    "location_lon": -71.0589,
    "description": "",
    "type": "Unknown",
    "source": "TechJobsForGood",
    "source_url": "https://www.techjobsforgood.com/jobs/32908/?ref=homepage",
    "posted": "2026-05-26T03:38:01.248Z",
    "impact_number": 0,
    "audit_number": 0,
    "audit_text": "",
    "tags": [
      "TechJobsForGood",
      "Mission Driven",
      "Tech"
    ],
    "ai_summary": "",
    "ai_red_flag_summary": "",
    "ai_score": 0,
    "ai_red_flag_score": 0,
    "ai_impact_summary": "",
    "ai_impact_score": 0
  },
  {
    "name": "Data Analyst The Partnership To End Homelessness New York, NY - $80K - $80K Data + Analytics We intervene to ensure they have a home to return to. We do more than address the immediate crisis—we bring the stability of home back into people’s lives by combining secure housing with wraparound services and community integration. Posted 1 week ago",
    "company_name": "Tech Jobs For Good",
    "location": "New York, NY",
    "remote": "Unknown",
    "location_lat": 40.7128,
    "location_lon": -74.006,
    "description": "",
    "type": "Unknown",
    "source": "TechJobsForGood",
    "source_url": "https://www.techjobsforgood.com/jobs/33173/?ref=homepage",
    "posted": "2026-05-26T03:38:01.248Z",
    "impact_number": 0,
    "audit_number": 0,
    "audit_text": "",
    "tags": [
      "TechJobsForGood",
      "Mission Driven",
      "Tech"
    ],
    "ai_summary": "",
    "ai_red_flag_summary": "",
    "ai_score": 0,
    "ai_red_flag_score": 0,
    "ai_impact_summary": "",
    "ai_impact_score": 0
  },
  {
    "name": "Staff Software Engineer Sofar Ocean San Francisco, CA - $175K - $220K Software Engineering Environment Climate Change Partners &amp; Advocates Sofar is the leading ocean intelligence platform. We&#39;ve built the world&#39;s largest real-time ocean sensor network, turning billions of measurements into insights trusted by scientists, governments, and the maritime industry alike. Posted 1 week ago",
    "company_name": "Tech Jobs For Good",
    "location": "San Francisco, CA",
    "remote": "Unknown",
    "location_lat": 37.7749,
    "location_lon": -122.4194,
    "description": "",
    "type": "Unknown",
    "source": "TechJobsForGood",
    "source_url": "https://www.techjobsforgood.com/jobs/33144/?ref=homepage",
    "posted": "2026-05-26T03:38:01.248Z",
    "impact_number": 0,
    "audit_number": 0,
    "audit_text": "",
    "tags": [
      "TechJobsForGood",
      "Mission Driven",
      "Tech"
    ],
    "ai_summary": "",
    "ai_red_flag_summary": "",
    "ai_score": 0,
    "ai_red_flag_score": 0,
    "ai_impact_summary": "",
    "ai_impact_score": 0
  },
  {
    "name": "Product Manager, Literacy Great Minds Remote (US) - $78K - $87K Product Great Minds is an education company that specializes in curriculum development and educational resources. Posted 3 days ago",
    "company_name": "Tech Jobs For Good",
    "location": "Unknown",
    "remote": "Remote",
    "location_lat": 26.4925331,
    "location_lon": 92.3308789,
    "description": "",
    "type": "Unknown",
    "source": "TechJobsForGood",
    "source_url": "https://www.techjobsforgood.com/jobs/33271/?ref=homepage",
    "posted": "2026-05-26T03:38:01.248Z",
    "impact_number": 0,
    "audit_number": 0,
    "audit_text": "",
    "tags": [
      "TechJobsForGood",
      "Mission Driven",
      "Tech"
    ],
    "ai_summary": "",
    "ai_red_flag_summary": "",
    "ai_score": 0,
    "ai_red_flag_score": 0,
    "ai_impact_summary": "",
    "ai_impact_score": 0
  },
  {
    "name": "Product Growth Manager Recidiviz New York, NY/Oakland, CA/Remote (US) - $93K - $120K Product Human Rights &amp; Equality Recidiviz is a non-profit technology company based in San Francisco, CA. We build common, open source technical infrastructure to help the criminal justice system end mass incarceration and focus on ongoing iteration towards better outcomes (both for the public and the individuals in the system). Posted 3 weeks ago",
    "company_name": "Tech Jobs For Good",
    "location": "New York, NY",
    "remote": "Remote",
    "location_lat": 40.7128,
    "location_lon": -74.006,
    "description": "",
    "type": "Unknown",
    "source": "TechJobsForGood",
    "source_url": "https://www.techjobsforgood.com/jobs/32903/?ref=homepage",
    "posted": "2026-05-26T03:38:01.248Z",
    "impact_number": 0,
    "audit_number": 0,
    "audit_text": "",
    "tags": [
      "TechJobsForGood",
      "Mission Driven",
      "Tech"
    ],
    "ai_summary": "",
    "ai_red_flag_summary": "",
    "ai_score": 0,
    "ai_red_flag_score": 0,
    "ai_impact_summary": "",
    "ai_impact_score": 0
  },
  {
    "name": "Senior Director, Data Platforms Great Minds Remote (US) - $207K - $222K Data + Analytics Great Minds is an education company that specializes in curriculum development and educational resources. Posted 3 days ago",
    "company_name": "Tech Jobs For Good",
    "location": "Unknown",
    "remote": "Remote",
    "location_lat": 26.4925331,
    "location_lon": 92.3308789,
    "description": "",
    "type": "Unknown",
    "source": "TechJobsForGood",
    "source_url": "https://www.techjobsforgood.com/jobs/33270/?ref=homepage",
    "posted": "2026-05-26T03:38:01.248Z",
    "impact_number": 0,
    "audit_number": 0,
    "audit_text": "",
    "tags": [
      "TechJobsForGood",
      "Mission Driven",
      "Tech"
    ],
    "ai_summary": "",
    "ai_red_flag_summary": "",
    "ai_score": 0,
    "ai_red_flag_score": 0,
    "ai_impact_summary": "",
    "ai_impact_score": 0
  },
  {
    "name": "IT Manager - Systems Administration Manager Energy Solutions Oakland, CA - $123K - $159K Information Technology Environment Clean Energy Climate Change Energy Solutions is focused on creating large-scale environmental impacts by providing cost-effective, market-based carbon, energy, and water management solutions. Posted 3 weeks ago",
    "company_name": "Tech Jobs For Good",
    "location": "Oakland, CA",
    "remote": "Unknown",
    "location_lat": 37.8044,
    "location_lon": -122.2712,
    "description": "",
    "type": "Unknown",
    "source": "TechJobsForGood",
    "source_url": "https://www.techjobsforgood.com/jobs/32961/?ref=homepage",
    "posted": "2026-05-26T03:38:01.248Z",
    "impact_number": 0,
    "audit_number": 0,
    "audit_text": "",
    "tags": [
      "TechJobsForGood",
      "Mission Driven",
      "Tech"
    ],
    "ai_summary": "",
    "ai_red_flag_summary": "",
    "ai_score": 0,
    "ai_red_flag_score": 0,
    "ai_impact_summary": "",
    "ai_impact_score": 0
  },
  {
    "name": "Software Engineer IV - Infra/SRE Mighty Acorn Remote (US) - $130K - $150K Software Engineering Partners &amp; Advocates Education Public Infrastructure Public Service &amp; Civic Engagement At Mighty Acorn, we make it easier for governments to deliver world-class digital services. From renewing a fishing license to applying for unemployment benefits, we build digital services that enhance public trust and satisfaction. Posted 2 weeks ago",
    "company_name": "Tech Jobs For Good",
    "location": "Unknown",
    "remote": "Remote",
    "location_lat": 26.4925331,
    "location_lon": 92.3308789,
    "description": "",
    "type": "Unknown",
    "source": "TechJobsForGood",
    "source_url": "https://www.techjobsforgood.com/jobs/33036/?ref=homepage",
    "posted": "2026-05-26T03:38:01.248Z",
    "impact_number": 0,
    "audit_number": 0,
    "audit_text": "",
    "tags": [
      "TechJobsForGood",
      "Mission Driven",
      "Tech"
    ],
    "ai_summary": "",
    "ai_red_flag_summary": "",
    "ai_score": 0,
    "ai_red_flag_score": 0,
    "ai_impact_summary": "",
    "ai_impact_score": 0
  },
  {
    "name": "Data Scientist, Center for Security and Emerging Technology (CSET) Georgetown University Washington, DC (Hybrid) - $80K - $157K Data + Analytics Education We’re a leading research university with a heart. Founded in the decade that the U.S. Constitution was signed, we’re the nation’s oldest Catholic and Jesuit university. Today we’re a forward-looking, diverse community devoted to social justice, restless inquiry and respect for each person’s individual needs and talents. Posted 3 weeks ago",
    "company_name": "Tech Jobs For Good",
    "location": "Washington, DC",
    "remote": "Unknown",
    "location_lat": 38.8950982,
    "location_lon": -77.0363849,
    "description": "",
    "type": "Unknown",
    "source": "TechJobsForGood",
    "source_url": "https://www.techjobsforgood.com/jobs/32900/?ref=homepage",
    "posted": "2026-05-26T03:38:01.248Z",
    "impact_number": 0,
    "audit_number": 0,
    "audit_text": "",
    "tags": [
      "TechJobsForGood",
      "Mission Driven",
      "Tech"
    ],
    "ai_summary": "",
    "ai_red_flag_summary": "",
    "ai_score": 0,
    "ai_red_flag_score": 0,
    "ai_impact_summary": "",
    "ai_impact_score": 0
  },
  {
    "name": "Full Stack Software Engineer UpMetrics Sacramento, CA - $145K - $170K Software Engineering Partners &amp; Advocates Leading social impact reporting platform Posted 4 weeks ago",
    "company_name": "Tech Jobs For Good",
    "location": "Sacramento, CA",
    "remote": "Unknown",
    "location_lat": 38.5816,
    "location_lon": -121.494,
    "description": "",
    "type": "Unknown",
    "source": "TechJobsForGood",
    "source_url": "https://www.techjobsforgood.com/jobs/32711/?ref=homepage",
    "posted": "2026-05-26T03:38:01.248Z",
    "impact_number": 0,
    "audit_number": 0,
    "audit_text": "",
    "tags": [
      "TechJobsForGood",
      "Mission Driven",
      "Tech"
    ],
    "ai_summary": "",
    "ai_red_flag_summary": "",
    "ai_score": 0,
    "ai_red_flag_score": 0,
    "ai_impact_summary": "",
    "ai_impact_score": 0
  },
  {
    "name": "Software Engineer V - Security Engineer Mighty Acorn Remote (US) - $150K - $200K Software Engineering Partners &amp; Advocates Education Public Infrastructure Public Service &amp; Civic Engagement At Mighty Acorn, we make it easier for governments to deliver world-class digital services. From renewing a fishing license to applying for unemployment benefits, we build digital services that enhance public trust and satisfaction. Posted 2 weeks ago",
    "company_name": "Tech Jobs For Good",
    "location": "Unknown",
    "remote": "Remote",
    "location_lat": 26.4925331,
    "location_lon": 92.3308789,
    "description": "",
    "type": "Unknown",
    "source": "TechJobsForGood",
    "source_url": "https://www.techjobsforgood.com/jobs/33034/?ref=homepage",
    "posted": "2026-05-26T03:38:01.248Z",
    "impact_number": 0,
    "audit_number": 0,
    "audit_text": "",
    "tags": [
      "TechJobsForGood",
      "Mission Driven",
      "Tech"
    ],
    "ai_summary": "",
    "ai_red_flag_summary": "",
    "ai_score": 0,
    "ai_red_flag_score": 0,
    "ai_impact_summary": "",
    "ai_impact_score": 0
  },
  {
    "name": "Manager, Policy and Data Analysis, Policy and Programs Northeast Energy Efficiency Partnerships Remote (US) - $70K - $80K Data + Analytics Northeast Energy Efficiency Partnerships is a nonprofit organization that drives regional collaboration to accelerate energy efficiency and reduce climate pollution in the Northeast and Mid-Atlantic. Posted 1 week ago",
    "company_name": "Tech Jobs For Good",
    "location": "Unknown",
    "remote": "Remote",
    "location_lat": 26.4925331,
    "location_lon": 92.3308789,
    "description": "",
    "type": "Unknown",
    "source": "TechJobsForGood",
    "source_url": "https://www.techjobsforgood.com/jobs/33175/?ref=homepage",
    "posted": "2026-05-26T03:38:01.248Z",
    "impact_number": 0,
    "audit_number": 0,
    "audit_text": "",
    "tags": [
      "TechJobsForGood",
      "Mission Driven",
      "Tech"
    ],
    "ai_summary": "",
    "ai_red_flag_summary": "",
    "ai_score": 0,
    "ai_red_flag_score": 0,
    "ai_impact_summary": "",
    "ai_impact_score": 0
  },
  {
    "name": "Software Engineer Flatiron Health New York, NY - $130K - $178K Software Engineering Health &amp; Well-Being Partners &amp; Advocates Accelerating the fight against cancer requires the entire industry to work together. Our products connect community oncologists, academics, hospitals, life science researchers and regulators on a shared technology platform. Together, we can learn from the experience of every patient. Posted 1 week ago",
    "company_name": "Tech Jobs For Good",
    "location": "New York, NY",
    "remote": "Unknown",
    "location_lat": 40.7128,
    "location_lon": -74.006,
    "description": "",
    "type": "Unknown",
    "source": "TechJobsForGood",
    "source_url": "https://www.techjobsforgood.com/jobs/33131/?ref=homepage",
    "posted": "2026-05-26T03:38:01.248Z",
    "impact_number": 0,
    "audit_number": 0,
    "audit_text": "",
    "tags": [
      "TechJobsForGood",
      "Mission Driven",
      "Tech"
    ],
    "ai_summary": "",
    "ai_red_flag_summary": "",
    "ai_score": 0,
    "ai_red_flag_score": 0,
    "ai_impact_summary": "",
    "ai_impact_score": 0
  },
  {
    "name": "Digital Designer Great Minds Washington, DC/Remote (US) - $66K - $72K Design + UX Great Minds is an education company that specializes in curriculum development and educational resources. Posted 4 days ago",
    "company_name": "Tech Jobs For Good",
    "location": "Washington, DC",
    "remote": "Remote",
    "location_lat": 38.8950982,
    "location_lon": -77.0363849,
    "description": "",
    "type": "Unknown",
    "source": "TechJobsForGood",
    "source_url": "https://www.techjobsforgood.com/jobs/33267/?ref=homepage",
    "posted": "2026-05-26T03:38:01.248Z",
    "impact_number": 0,
    "audit_number": 0,
    "audit_text": "",
    "tags": [
      "TechJobsForGood",
      "Mission Driven",
      "Tech"
    ],
    "ai_summary": "",
    "ai_red_flag_summary": "",
    "ai_score": 0,
    "ai_red_flag_score": 0,
    "ai_impact_summary": "",
    "ai_impact_score": 0
  },
  {
    "name": "i-team Civic Designer, Lansing, MI (Lansing Innovation Team) Johns Hopkins University Lansing, MI - $63K - $110K Design + UX Education Public Service &amp; Civic Engagement Johns Hopkins University is a private research university in Baltimore, Maryland. Founded in 1876, Johns Hopkins was the first American university based on the European research institution model. Posted 2 weeks ago",
    "company_name": "Tech Jobs For Good",
    "location": "Lansing, MI",
    "remote": "Unknown",
    "location_lat": 42.7338254,
    "location_lon": -84.5546295,
    "description": "",
    "type": "Unknown",
    "source": "TechJobsForGood",
    "source_url": "https://www.techjobsforgood.com/jobs/33033/?ref=homepage",
    "posted": "2026-05-26T03:38:01.248Z",
    "impact_number": 0,
    "audit_number": 0,
    "audit_text": "",
    "tags": [
      "TechJobsForGood",
      "Mission Driven",
      "Tech"
    ],
    "ai_summary": "",
    "ai_red_flag_summary": "",
    "ai_score": 0,
    "ai_red_flag_score": 0,
    "ai_impact_summary": "",
    "ai_impact_score": 0
  },
  {
    "name": "Senior Visual Communications Designer Sofar Ocean San Francisco, CA (Hybrid) - $120K - $170K Design + UX Environment Climate Change Partners &amp; Advocates Sofar is the leading ocean intelligence platform. We&#39;ve built the world&#39;s largest real-time ocean sensor network, turning billions of measurements into insights trusted by scientists, governments, and the maritime industry alike. Posted 1 week ago",
    "company_name": "Tech Jobs For Good",
    "location": "San Francisco, CA",
    "remote": "Unknown",
    "location_lat": 37.7749,
    "location_lon": -122.4194,
    "description": "",
    "type": "Unknown",
    "source": "TechJobsForGood",
    "source_url": "https://www.techjobsforgood.com/jobs/33145/?ref=homepage",
    "posted": "2026-05-26T03:38:01.248Z",
    "impact_number": 0,
    "audit_number": 0,
    "audit_text": "",
    "tags": [
      "TechJobsForGood",
      "Mission Driven",
      "Tech"
    ],
    "ai_summary": "",
    "ai_red_flag_summary": "",
    "ai_score": 0,
    "ai_red_flag_score": 0,
    "ai_impact_summary": "",
    "ai_impact_score": 0
  },
  {
    "name": "Software Engineer V - Infra/SRE Mighty Acorn Remote (US) - $150K - $200K Software Engineering Partners &amp; Advocates Education Public Infrastructure Public Service &amp; Civic Engagement At Mighty Acorn, we make it easier for governments to deliver world-class digital services. From renewing a fishing license to applying for unemployment benefits, we build digital services that enhance public trust and satisfaction. Posted 3 weeks ago",
    "company_name": "Tech Jobs For Good",
    "location": "Unknown",
    "remote": "Remote",
    "location_lat": 26.4925331,
    "location_lon": 92.3308789,
    "description": "",
    "type": "Unknown",
    "source": "TechJobsForGood",
    "source_url": "https://www.techjobsforgood.com/jobs/32891/?ref=homepage",
    "posted": "2026-05-26T03:38:01.248Z",
    "impact_number": 0,
    "audit_number": 0,
    "audit_text": "",
    "tags": [
      "TechJobsForGood",
      "Mission Driven",
      "Tech"
    ],
    "ai_summary": "",
    "ai_red_flag_summary": "",
    "ai_score": 0,
    "ai_red_flag_score": 0,
    "ai_impact_summary": "",
    "ai_impact_score": 0
  },
  {
    "name": "Data Engineering Director Courier Newsroom Remote (US) - $130K - $140K Data + Analytics Public Infrastructure Public Service &amp; Civic Engagement COURIER is an independent advocacy news/media network that builds a more informed, engaged, and representative America by reaching audiences where they are online with factual, values-driven news and analysis. Posted 4 weeks ago",
    "company_name": "Tech Jobs For Good",
    "location": "Unknown",
    "remote": "Remote",
    "location_lat": 26.4925331,
    "location_lon": 92.3308789,
    "description": "",
    "type": "Unknown",
    "source": "TechJobsForGood",
    "source_url": "https://www.techjobsforgood.com/jobs/32707/?ref=homepage",
    "posted": "2026-05-26T03:38:01.248Z",
    "impact_number": 0,
    "audit_number": 0,
    "audit_text": "",
    "tags": [
      "TechJobsForGood",
      "Mission Driven",
      "Tech"
    ],
    "ai_summary": "",
    "ai_red_flag_summary": "",
    "ai_score": 0,
    "ai_red_flag_score": 0,
    "ai_impact_summary": "",
    "ai_impact_score": 0
  },
  {
    "name": "Sr. Data Engineer Kalderos Chicago, IL/Boston, MA/Remote - $145K - $175K Data + Analytics Health &amp; Well-Being Partners &amp; Advocates Kalderos delivers unifying technology that solves problems facing the U.S. healthcare system. We work with healthcare providers, manufacturers, payers and others to increase transparency and restore trust — enabling everyone to focus on improving the health of people. Posted 4 days ago",
    "company_name": "Tech Jobs For Good",
    "location": "Chicago, IL",
    "remote": "Remote",
    "location_lat": 41.8781,
    "location_lon": -87.6298,
    "description": "",
    "type": "Unknown",
    "source": "TechJobsForGood",
    "source_url": "https://www.techjobsforgood.com/jobs/33265/?ref=homepage",
    "posted": "2026-05-26T03:38:01.248Z",
    "impact_number": 0,
    "audit_number": 0,
    "audit_text": "",
    "tags": [
      "TechJobsForGood",
      "Mission Driven",
      "Tech"
    ],
    "ai_summary": "",
    "ai_red_flag_summary": "",
    "ai_score": 0,
    "ai_red_flag_score": 0,
    "ai_impact_summary": "",
    "ai_impact_score": 0
  },
  {
    "name": "Product Manager - Energy Code at Ekotrope Ekotrope Boston, MA/Remote (US) - $110K - $120K Product Clean Energy Ekotrope was founded in 2011 with the mission to empower people with technology and insights to drive informed decisions that move our built environment towards sustainability. Posted 3 weeks ago",
    "company_name": "Tech Jobs For Good",
    "location": "Boston, MA",
    "remote": "Remote",
    "location_lat": 42.3601,
    "location_lon": -71.0589,
    "description": "",
    "type": "Unknown",
    "source": "TechJobsForGood",
    "source_url": "https://www.techjobsforgood.com/jobs/32906/?ref=homepage",
    "posted": "2026-05-26T03:38:01.248Z",
    "impact_number": 0,
    "audit_number": 0,
    "audit_text": "",
    "tags": [
      "TechJobsForGood",
      "Mission Driven",
      "Tech"
    ],
    "ai_summary": "",
    "ai_red_flag_summary": "",
    "ai_score": 0,
    "ai_red_flag_score": 0,
    "ai_impact_summary": "",
    "ai_impact_score": 0
  },
  {
    "name": "Senior Product Analyst Art of Problem Solving San Diego, CA (Hybrid) - $150K - $180K Data + Analytics Education Art of Problem Solving (AoPS) is on a mission to discover, inspire, and train the great problem solvers of the next generation. Since 2003, we have trained hundreds of thousands of the country’s top students, through our online school, in-person academies, textbooks, and online learning systems. Posted 3 weeks ago",
    "company_name": "Tech Jobs For Good",
    "location": "San Diego, CA",
    "remote": "Unknown",
    "location_lat": 32.7174202,
    "location_lon": -117.162772,
    "description": "",
    "type": "Unknown",
    "source": "TechJobsForGood",
    "source_url": "https://www.techjobsforgood.com/jobs/32774/?ref=homepage",
    "posted": "2026-05-26T03:38:01.248Z",
    "impact_number": 0,
    "audit_number": 0,
    "audit_text": "",
    "tags": [
      "TechJobsForGood",
      "Mission Driven",
      "Tech"
    ],
    "ai_summary": "",
    "ai_red_flag_summary": "",
    "ai_score": 0,
    "ai_red_flag_score": 0,
    "ai_impact_summary": "",
    "ai_impact_score": 0
  },
  {
    "name": "Associate Director, Security &amp; Compliance Great Minds Remote (US) - $167K - $183K Information Technology Great Minds is an education company that specializes in curriculum development and educational resources. Posted 3 days ago",
    "company_name": "Tech Jobs For Good",
    "location": "Unknown",
    "remote": "Remote",
    "location_lat": 26.4925331,
    "location_lon": 92.3308789,
    "description": "",
    "type": "Unknown",
    "source": "TechJobsForGood",
    "source_url": "https://www.techjobsforgood.com/jobs/33269/?ref=homepage",
    "posted": "2026-05-26T03:38:01.248Z",
    "impact_number": 0,
    "audit_number": 0,
    "audit_text": "",
    "tags": [
      "TechJobsForGood",
      "Mission Driven",
      "Tech"
    ],
    "ai_summary": "",
    "ai_red_flag_summary": "",
    "ai_score": 0,
    "ai_red_flag_score": 0,
    "ai_impact_summary": "",
    "ai_impact_score": 0
  },
  {
    "name": "IT Manager Northwest Indian Fisheries Commission Olympia, WA (Hybrid) / Seattle, WA / Tacoma, WA - $73K - $135K Information Technology Climate Change Environment Northwest Indian Fisheries Commission is a support service organization for 20 treaty Indian tribes in western Washington, focused on assisting member tribes with natural resources management. Posted 4 weeks ago",
    "company_name": "Tech Jobs For Good",
    "location": "Olympia, WA",
    "remote": "Unknown",
    "location_lat": 47.0451022,
    "location_lon": -122.8950075,
    "description": "",
    "type": "Unknown",
    "source": "TechJobsForGood",
    "source_url": "https://www.techjobsforgood.com/jobs/32710/?ref=homepage",
    "posted": "2026-05-26T03:38:01.248Z",
    "impact_number": 0,
    "audit_number": 0,
    "audit_text": "",
    "tags": [
      "TechJobsForGood",
      "Mission Driven",
      "Tech"
    ],
    "ai_summary": "",
    "ai_red_flag_summary": "",
    "ai_score": 0,
    "ai_red_flag_score": 0,
    "ai_impact_summary": "",
    "ai_impact_score": 0
  },
  {
    "name": "Director of Product, Customer Experience Art of Problem Solving San Diego, CA (Hybrid) - $170K - $210K Product Education Art of Problem Solving (AoPS) is on a mission to discover, inspire, and train the great problem solvers of the next generation. Since 2003, we have trained hundreds of thousands of the country’s top students, through our online school, in-person academies, textbooks, and online learning systems. Posted 3 weeks ago",
    "company_name": "Tech Jobs For Good",
    "location": "San Diego, CA",
    "remote": "Unknown",
    "location_lat": 32.7174202,
    "location_lon": -117.162772,
    "description": "",
    "type": "Unknown",
    "source": "TechJobsForGood",
    "source_url": "https://www.techjobsforgood.com/jobs/32772/?ref=homepage",
    "posted": "2026-05-26T03:38:01.248Z",
    "impact_number": 0,
    "audit_number": 0,
    "audit_text": "",
    "tags": [
      "TechJobsForGood",
      "Mission Driven",
      "Tech"
    ],
    "ai_summary": "",
    "ai_red_flag_summary": "",
    "ai_score": 0,
    "ai_red_flag_score": 0,
    "ai_impact_summary": "",
    "ai_impact_score": 0
  },
  {
    "name": "Product Designer II Art of Problem Solving San Diego, CA (Hybrid) - $90K - $125K Design + UX Education Art of Problem Solving (AoPS) is on a mission to discover, inspire, and train the great problem solvers of the next generation. Since 2003, we have trained hundreds of thousands of the country’s top students, through our online school, in-person academies, textbooks, and online learning systems. Posted 1 month ago",
    "company_name": "Tech Jobs For Good",
    "location": "San Diego, CA",
    "remote": "Unknown",
    "location_lat": 32.7174202,
    "location_lon": -117.162772,
    "description": "",
    "type": "Unknown",
    "source": "TechJobsForGood",
    "source_url": "https://www.techjobsforgood.com/jobs/32387/?ref=homepage",
    "posted": "2026-05-26T03:38:01.248Z",
    "impact_number": 0,
    "audit_number": 0,
    "audit_text": "",
    "tags": [
      "TechJobsForGood",
      "Mission Driven",
      "Tech"
    ],
    "ai_summary": "",
    "ai_red_flag_summary": "",
    "ai_score": 0,
    "ai_red_flag_score": 0,
    "ai_impact_summary": "",
    "ai_impact_score": 0
  },
  {
    "name": "Senior Associate/Manager, Quantitative Analytics Cypress Creek Renewables Chicago, IL/New York, NY - $150K - $175K Data + Analytics Clean Energy Powering A Sustainable Future, One Project At A Time Posted 4 days ago",
    "company_name": "Tech Jobs For Good",
    "location": "Chicago, IL",
    "remote": "Unknown",
    "location_lat": 41.8781,
    "location_lon": -87.6298,
    "description": "",
    "type": "Unknown",
    "source": "TechJobsForGood",
    "source_url": "https://www.techjobsforgood.com/jobs/33257/?ref=homepage",
    "posted": "2026-05-26T03:38:01.248Z",
    "impact_number": 0,
    "audit_number": 0,
    "audit_text": "",
    "tags": [
      "TechJobsForGood",
      "Mission Driven",
      "Tech"
    ],
    "ai_summary": "",
    "ai_red_flag_summary": "",
    "ai_score": 0,
    "ai_red_flag_score": 0,
    "ai_impact_summary": "",
    "ai_impact_score": 0
  },
  {
    "name": "Data &amp; Reporting Analyst Collective Health Lehi, UT/Plano, TX - $77K - $106K Data + Analytics Partners &amp; Advocates Health &amp; Well-Being Collective Health is on a mission to make it effortless for organizations and their people to understand, navigate and pay for their healthcare. Collective Health combines technology, design, and a human touch to allow benefits teams to deliver a truly enjoyable healthcare experience to their employees while also equipping benefits teams and their consulting partners with the data and insights necessary to help develop effective and efficient benefits strategies. Posted 4 days ago",
    "company_name": "Tech Jobs For Good",
    "location": "Lehi, UT",
    "remote": "Unknown",
    "location_lat": 40.3881114,
    "location_lon": -111.8486019,
    "description": "",
    "type": "Unknown",
    "source": "TechJobsForGood",
    "source_url": "https://www.techjobsforgood.com/jobs/33258/?ref=homepage",
    "posted": "2026-05-26T03:38:01.248Z",
    "impact_number": 0,
    "audit_number": 0,
    "audit_text": "",
    "tags": [
      "TechJobsForGood",
      "Mission Driven",
      "Tech"
    ],
    "ai_summary": "",
    "ai_red_flag_summary": "",
    "ai_score": 0,
    "ai_red_flag_score": 0,
    "ai_impact_summary": "",
    "ai_impact_score": 0
  },
  {
    "name": "Product Design Intern Understood New York, NY - $25 Per Hour Product Education Health &amp; Well-Being Partners &amp; Advocates Our goal is to help the millions of parents whose children, ages 3–20, are struggling with learning and attention issues. We want to empower them to understand their children’s issues and relate to their experiences. With this knowledge, parents can make effective choices that propel their children from simply coping to truly thriving. Posted 1 week ago",
    "company_name": "Tech Jobs For Good",
    "location": "New York, NY",
    "remote": "Unknown",
    "location_lat": 40.7128,
    "location_lon": -74.006,
    "description": "",
    "type": "Unknown",
    "source": "TechJobsForGood",
    "source_url": "https://www.techjobsforgood.com/jobs/33129/?ref=homepage",
    "posted": "2026-05-26T03:38:01.248Z",
    "impact_number": 0,
    "audit_number": 0,
    "audit_text": "",
    "tags": [
      "TechJobsForGood",
      "Mission Driven",
      "Tech"
    ],
    "ai_summary": "",
    "ai_red_flag_summary": "",
    "ai_score": 0,
    "ai_red_flag_score": 0,
    "ai_impact_summary": "",
    "ai_impact_score": 0
  },
  {
    "name": "Product Engineer One Project Remote (US) - $175K - $200K Software Engineering Partners &amp; Advocates Economic Development We are joining with all who dream of a world beyond capitalism, today. Posted 1 month ago",
    "company_name": "Tech Jobs For Good",
    "location": "Unknown",
    "remote": "Remote",
    "location_lat": 26.4925331,
    "location_lon": 92.3308789,
    "description": "",
    "type": "Unknown",
    "source": "TechJobsForGood",
    "source_url": "https://www.techjobsforgood.com/jobs/32347/?ref=homepage",
    "posted": "2026-05-26T03:38:01.248Z",
    "impact_number": 0,
    "audit_number": 0,
    "audit_text": "",
    "tags": [
      "TechJobsForGood",
      "Mission Driven",
      "Tech"
    ],
    "ai_summary": "",
    "ai_red_flag_summary": "",
    "ai_score": 0,
    "ai_red_flag_score": 0,
    "ai_impact_summary": "",
    "ai_impact_score": 0
  },
  {
    "name": "Senior Full-Stack Engineer Understood New York, NY - $155K - $175K Information Technology Education Health &amp; Well-Being Partners &amp; Advocates Our goal is to help the millions of parents whose children, ages 3–20, are struggling with learning and attention issues. We want to empower them to understand their children’s issues and relate to their experiences. With this knowledge, parents can make effective choices that propel their children from simply coping to truly thriving. Posted 1 week ago",
    "company_name": "Tech Jobs For Good",
    "location": "New York, NY",
    "remote": "Unknown",
    "location_lat": 40.7128,
    "location_lon": -74.006,
    "description": "",
    "type": "Unknown",
    "source": "TechJobsForGood",
    "source_url": "https://www.techjobsforgood.com/jobs/33130/?ref=homepage",
    "posted": "2026-05-26T03:38:01.248Z",
    "impact_number": 0,
    "audit_number": 0,
    "audit_text": "",
    "tags": [
      "TechJobsForGood",
      "Mission Driven",
      "Tech"
    ],
    "ai_summary": "",
    "ai_red_flag_summary": "",
    "ai_score": 0,
    "ai_red_flag_score": 0,
    "ai_impact_summary": "",
    "ai_impact_score": 0
  },
  {
    "name": "Fullstack - Data Platform (Autonomy) Zipline South San Francisco, CA - $170K - $210K Data + Analytics Health &amp; Well-Being Global Peace &amp; Safety Climate Change We created Zipline to deliver medicine via drone to those who need it most Posted 1 week ago",
    "company_name": "Tech Jobs For Good",
    "location": "South San Francisco, CA",
    "remote": "Unknown",
    "location_lat": 50.9097,
    "location_lon": -1.4044,
    "description": "",
    "type": "Unknown",
    "source": "TechJobsForGood",
    "source_url": "https://www.techjobsforgood.com/jobs/33127/?ref=homepage",
    "posted": "2026-05-26T03:38:01.248Z",
    "impact_number": 0,
    "audit_number": 0,
    "audit_text": "",
    "tags": [
      "TechJobsForGood",
      "Mission Driven",
      "Tech"
    ],
    "ai_summary": "",
    "ai_red_flag_summary": "",
    "ai_score": 0,
    "ai_red_flag_score": 0,
    "ai_impact_summary": "",
    "ai_impact_score": 0
  },
  {
    "name": "Readiness &amp; Test Project Manager NYC Office of Technology and Innovation New York, NY - $75K - $125K Information Technology Public Service &amp; Civic Engagement Partners &amp; Advocates Public Infrastructure We see technology as a tool for realizing Mayor de Blasio’s vision of making New York City the fairest big city in America. Technology can deliver inclusiveness, accessibility, and economic opportunity. We work to make this happen. Posted 4 weeks ago",
    "company_name": "Tech Jobs For Good",
    "location": "New York, NY",
    "remote": "Unknown",
    "location_lat": 40.7128,
    "location_lon": -74.006,
    "description": "",
    "type": "Unknown",
    "source": "TechJobsForGood",
    "source_url": "https://www.techjobsforgood.com/jobs/32676/?ref=homepage",
    "posted": "2026-05-26T03:38:01.248Z",
    "impact_number": 0,
    "audit_number": 0,
    "audit_text": "",
    "tags": [
      "TechJobsForGood",
      "Mission Driven",
      "Tech"
    ],
    "ai_summary": "",
    "ai_red_flag_summary": "",
    "ai_score": 0,
    "ai_red_flag_score": 0,
    "ai_impact_summary": "",
    "ai_impact_score": 0
  },
  {
    "name": "Summer 2026 Marketing Designer Intern Art of Problem Solving San Diego, CA - $30 Per Hour Design + UX Education Art of Problem Solving (AoPS) is on a mission to discover, inspire, and train the great problem solvers of the next generation. Since 2003, we have trained hundreds of thousands of the country’s top students, through our online school, in-person academies, textbooks, and online learning systems. Posted 3 weeks ago",
    "company_name": "Tech Jobs For Good",
    "location": "San Diego, CA",
    "remote": "Unknown",
    "location_lat": 32.7174202,
    "location_lon": -117.162772,
    "description": "",
    "type": "Unknown",
    "source": "TechJobsForGood",
    "source_url": "https://www.techjobsforgood.com/jobs/32773/?ref=homepage",
    "posted": "2026-05-26T03:38:01.248Z",
    "impact_number": 0,
    "audit_number": 0,
    "audit_text": "",
    "tags": [
      "TechJobsForGood",
      "Mission Driven",
      "Tech"
    ],
    "ai_summary": "",
    "ai_red_flag_summary": "",
    "ai_score": 0,
    "ai_red_flag_score": 0,
    "ai_impact_summary": "",
    "ai_impact_score": 0
  },
  {
    "name": "Senior Product Manager ChargePoint Campbell, CA (Hybrid) - $85K - $225K Product Clean Energy ChargePoint develops and manufactures technology for their network of electrical vehicle charging stations. Posted 4 days ago",
    "company_name": "Tech Jobs For Good",
    "location": "Campbell, CA",
    "remote": "Unknown",
    "location_lat": 37.2870626,
    "location_lon": -121.944881,
    "description": "",
    "type": "Unknown",
    "source": "TechJobsForGood",
    "source_url": "https://www.techjobsforgood.com/jobs/33262/?ref=homepage",
    "posted": "2026-05-26T03:38:01.248Z",
    "impact_number": 0,
    "audit_number": 0,
    "audit_text": "",
    "tags": [
      "TechJobsForGood",
      "Mission Driven",
      "Tech"
    ],
    "ai_summary": "",
    "ai_red_flag_summary": "",
    "ai_score": 0,
    "ai_red_flag_score": 0,
    "ai_impact_summary": "",
    "ai_impact_score": 0
  },
  {
    "name": "Senior Full Stack Software Developer Nexamp Boston, MA (Hybrid) - $170K - $190K Software Engineering Clean Energy Partners &amp; Advocates Nexamp is leading the transformation to the new energy economy with proven solutions for the deployment and operation of solar energy assets. Our comprehensive capabilities span the entire solar project lifecycle – from project development, design and construction, through financing, operations, and maintenance. Posted 4 days ago",
    "company_name": "Tech Jobs For Good",
    "location": "Boston, MA",
    "remote": "Unknown",
    "location_lat": 42.3601,
    "location_lon": -71.0589,
    "description": "",
    "type": "Unknown",
    "source": "TechJobsForGood",
    "source_url": "https://www.techjobsforgood.com/jobs/33264/?ref=homepage",
    "posted": "2026-05-26T03:38:01.248Z",
    "impact_number": 0,
    "audit_number": 0,
    "audit_text": "",
    "tags": [
      "TechJobsForGood",
      "Mission Driven",
      "Tech"
    ],
    "ai_summary": "",
    "ai_red_flag_summary": "",
    "ai_score": 0,
    "ai_red_flag_score": 0,
    "ai_impact_summary": "",
    "ai_impact_score": 0
  },
  {
    "name": "Social Media Summer Intern 2026 Pachamama Alliance San Francisco, CA - $20 Per Hour Information Technology Pachamama Alliance is a non-profit organization that focuses on environmental conservation, social justice, and community development. Posted 1 week ago",
    "company_name": "Tech Jobs For Good",
    "location": "San Francisco, CA",
    "remote": "Unknown",
    "location_lat": 37.7749,
    "location_lon": -122.4194,
    "description": "",
    "type": "Unknown",
    "source": "TechJobsForGood",
    "source_url": "https://www.techjobsforgood.com/jobs/33176/?ref=homepage",
    "posted": "2026-05-26T03:38:01.248Z",
    "impact_number": 0,
    "audit_number": 0,
    "audit_text": "",
    "tags": [
      "TechJobsForGood",
      "Mission Driven",
      "Tech"
    ],
    "ai_summary": "",
    "ai_red_flag_summary": "",
    "ai_score": 0,
    "ai_red_flag_score": 0,
    "ai_impact_summary": "",
    "ai_impact_score": 0
  },
  {
    "name": "Director, Digital Product Pivot Bio Minnetonka, MN/St. Louis, MO - $168K - $210K Product Climate Change Environment Food &amp; Agriculture Pivot Bio was born out of an ambition to replace synthetic nitrogen fertilizer with a more sustainable and safer tool for farmers. Our microbes can be grown on sugar and water with next to no carbon emissions, and the nitrogen they produce stays at the root of the plant where it belongs. With nitrogen-fixing microbes, we didn’t just develop a sustainable product - we’ve created nitrogen’s turning point and a better tool for farmers across the globe. Posted 2 weeks ago",
    "company_name": "Tech Jobs For Good",
    "location": "Minnetonka, MN",
    "remote": "Unknown",
    "location_lat": 44.9405086,
    "location_lon": -93.4638936,
    "description": "",
    "type": "Unknown",
    "source": "TechJobsForGood",
    "source_url": "https://www.techjobsforgood.com/jobs/32964/?ref=homepage",
    "posted": "2026-05-26T03:38:01.248Z",
    "impact_number": 0,
    "audit_number": 0,
    "audit_text": "",
    "tags": [
      "TechJobsForGood",
      "Mission Driven",
      "Tech"
    ],
    "ai_summary": "",
    "ai_red_flag_summary": "",
    "ai_score": 0,
    "ai_red_flag_score": 0,
    "ai_impact_summary": "",
    "ai_impact_score": 0
  },
  {
    "name": "Senior Product Designer, Clinical Workflows Flatiron Health New York, NY - $136K - $187K Product Health &amp; Well-Being Partners &amp; Advocates Accelerating the fight against cancer requires the entire industry to work together. Our products connect community oncologists, academics, hospitals, life science researchers and regulators on a shared technology platform. Together, we can learn from the experience of every patient. Posted 1 week ago",
    "company_name": "Tech Jobs For Good",
    "location": "New York, NY",
    "remote": "Unknown",
    "location_lat": 40.7128,
    "location_lon": -74.006,
    "description": "",
    "type": "Unknown",
    "source": "TechJobsForGood",
    "source_url": "https://www.techjobsforgood.com/jobs/33133/?ref=homepage",
    "posted": "2026-05-26T03:38:01.248Z",
    "impact_number": 0,
    "audit_number": 0,
    "audit_text": "",
    "tags": [
      "TechJobsForGood",
      "Mission Driven",
      "Tech"
    ],
    "ai_summary": "",
    "ai_red_flag_summary": "",
    "ai_score": 0,
    "ai_red_flag_score": 0,
    "ai_impact_summary": "",
    "ai_impact_score": 0
  },
  {
    "name": "Senior Software Engineer ChargePoint Campbell, CA - $142K - $200K Software Engineering Clean Energy ChargePoint develops and manufactures technology for their network of electrical vehicle charging stations. Posted 4 days ago",
    "company_name": "Tech Jobs For Good",
    "location": "Campbell, CA",
    "remote": "Unknown",
    "location_lat": 37.2870626,
    "location_lon": -121.944881,
    "description": "",
    "type": "Unknown",
    "source": "TechJobsForGood",
    "source_url": "https://www.techjobsforgood.com/jobs/33261/?ref=homepage",
    "posted": "2026-05-26T03:38:01.248Z",
    "impact_number": 0,
    "audit_number": 0,
    "audit_text": "",
    "tags": [
      "TechJobsForGood",
      "Mission Driven",
      "Tech"
    ],
    "ai_summary": "",
    "ai_red_flag_summary": "",
    "ai_score": 0,
    "ai_red_flag_score": 0,
    "ai_impact_summary": "",
    "ai_impact_score": 0
  },
  {
    "name": "CRM Developer NYC Office of Technology and Innovation New York, NY - $68K - $135K Information Technology Public Service &amp; Civic Engagement Partners &amp; Advocates Public Infrastructure We see technology as a tool for realizing Mayor de Blasio’s vision of making New York City the fairest big city in America. Technology can deliver inclusiveness, accessibility, and economic opportunity. We work to make this happen. Posted 4 weeks ago",
    "company_name": "Tech Jobs For Good",
    "location": "New York, NY",
    "remote": "Unknown",
    "location_lat": 40.7128,
    "location_lon": -74.006,
    "description": "",
    "type": "Unknown",
    "source": "TechJobsForGood",
    "source_url": "https://www.techjobsforgood.com/jobs/32674/?ref=homepage",
    "posted": "2026-05-26T03:38:01.248Z",
    "impact_number": 0,
    "audit_number": 0,
    "audit_text": "",
    "tags": [
      "TechJobsForGood",
      "Mission Driven",
      "Tech"
    ],
    "ai_summary": "",
    "ai_red_flag_summary": "",
    "ai_score": 0,
    "ai_red_flag_score": 0,
    "ai_impact_summary": "",
    "ai_impact_score": 0
  },
  {
    "name": "Staff Software Engineer Copper Berkeley, CA - $190K - $228K Software Engineering We make appliances with integrated battery energy storage. Posted 4 weeks ago",
    "company_name": "Tech Jobs For Good",
    "location": "Berkeley, CA",
    "remote": "Unknown",
    "location_lat": 37.8716,
    "location_lon": -122.2727,
    "description": "",
    "type": "Unknown",
    "source": "TechJobsForGood",
    "source_url": "https://www.techjobsforgood.com/jobs/32672/?ref=homepage",
    "posted": "2026-05-26T03:38:01.248Z",
    "impact_number": 0,
    "audit_number": 0,
    "audit_text": "",
    "tags": [
      "TechJobsForGood",
      "Mission Driven",
      "Tech"
    ],
    "ai_summary": "",
    "ai_red_flag_summary": "",
    "ai_score": 0,
    "ai_red_flag_score": 0,
    "ai_impact_summary": "",
    "ai_impact_score": 0
  },
  {
    "name": "Autonomy Software Engineer Zipline South San Francisco, CA - $200K - $265K Software Engineering Health &amp; Well-Being Global Peace &amp; Safety Climate Change We created Zipline to deliver medicine via drone to those who need it most Posted 1 week ago",
    "company_name": "Tech Jobs For Good",
    "location": "South San Francisco, CA",
    "remote": "Unknown",
    "location_lat": 50.9097,
    "location_lon": -1.4044,
    "description": "",
    "type": "Unknown",
    "source": "TechJobsForGood",
    "source_url": "https://www.techjobsforgood.com/jobs/33128/?ref=homepage",
    "posted": "2026-05-26T03:38:01.248Z",
    "impact_number": 0,
    "audit_number": 0,
    "audit_text": "",
    "tags": [
      "TechJobsForGood",
      "Mission Driven",
      "Tech"
    ],
    "ai_summary": "",
    "ai_red_flag_summary": "",
    "ai_score": 0,
    "ai_red_flag_score": 0,
    "ai_impact_summary": "",
    "ai_impact_score": 0
  },
  {
    "name": "Forward Deployed Software Engineer Flatiron Health New York, NY - $130K - $178K Software Engineering Health &amp; Well-Being Partners &amp; Advocates Accelerating the fight against cancer requires the entire industry to work together. Our products connect community oncologists, academics, hospitals, life science researchers and regulators on a shared technology platform. Together, we can learn from the experience of every patient. Posted 1 week ago",
    "company_name": "Tech Jobs For Good",
    "location": "New York, NY",
    "remote": "Unknown",
    "location_lat": 40.7128,
    "location_lon": -74.006,
    "description": "",
    "type": "Unknown",
    "source": "TechJobsForGood",
    "source_url": "https://www.techjobsforgood.com/jobs/33132/?ref=homepage",
    "posted": "2026-05-26T03:38:01.248Z",
    "impact_number": 0,
    "audit_number": 0,
    "audit_text": "",
    "tags": [
      "TechJobsForGood",
      "Mission Driven",
      "Tech"
    ],
    "ai_summary": "",
    "ai_red_flag_summary": "",
    "ai_score": 0,
    "ai_red_flag_score": 0,
    "ai_impact_summary": "",
    "ai_impact_score": 0
  },
  {
    "name": "IT Security Manager Great Minds Remote (US) - $146K - $166K Information Technology Great Minds is an education company that specializes in curriculum development and educational resources. Posted 4 days ago",
    "company_name": "Tech Jobs For Good",
    "location": "Unknown",
    "remote": "Remote",
    "location_lat": 26.4925331,
    "location_lon": 92.3308789,
    "description": "",
    "type": "Unknown",
    "source": "TechJobsForGood",
    "source_url": "https://www.techjobsforgood.com/jobs/33273/?ref=homepage",
    "posted": "2026-05-26T03:38:01.248Z",
    "impact_number": 0,
    "audit_number": 0,
    "audit_text": "",
    "tags": [
      "TechJobsForGood",
      "Mission Driven",
      "Tech"
    ],
    "ai_summary": "",
    "ai_red_flag_summary": "",
    "ai_score": 0,
    "ai_red_flag_score": 0,
    "ai_impact_summary": "",
    "ai_impact_score": 0
  },
  {
    "name": "Senior Product Manager, Business Processes Nexamp Boston, MA (Hybrid) - $155K - $175K Product Clean Energy Partners &amp; Advocates Nexamp is leading the transformation to the new energy economy with proven solutions for the deployment and operation of solar energy assets. Our comprehensive capabilities span the entire solar project lifecycle – from project development, design and construction, through financing, operations, and maintenance. Posted 4 days ago",
    "company_name": "Tech Jobs For Good",
    "location": "Boston, MA",
    "remote": "Unknown",
    "location_lat": 42.3601,
    "location_lon": -71.0589,
    "description": "",
    "type": "Unknown",
    "source": "TechJobsForGood",
    "source_url": "https://www.techjobsforgood.com/jobs/33263/?ref=homepage",
    "posted": "2026-05-26T03:38:01.248Z",
    "impact_number": 0,
    "audit_number": 0,
    "audit_text": "",
    "tags": [
      "TechJobsForGood",
      "Mission Driven",
      "Tech"
    ],
    "ai_summary": "",
    "ai_red_flag_summary": "",
    "ai_score": 0,
    "ai_red_flag_score": 0,
    "ai_impact_summary": "",
    "ai_impact_score": 0
  },
  {
    "name": "GIS Application Developer NYC Office of Technology and Innovation New York, NY - $68K - $125K Information Technology Public Service &amp; Civic Engagement Partners &amp; Advocates Public Infrastructure We see technology as a tool for realizing Mayor de Blasio’s vision of making New York City the fairest big city in America. Technology can deliver inclusiveness, accessibility, and economic opportunity. We work to make this happen. Posted 4 weeks ago",
    "company_name": "Tech Jobs For Good",
    "location": "New York, NY",
    "remote": "Unknown",
    "location_lat": 40.7128,
    "location_lon": -74.006,
    "description": "",
    "type": "Unknown",
    "source": "TechJobsForGood",
    "source_url": "https://www.techjobsforgood.com/jobs/32679/?ref=homepage",
    "posted": "2026-05-26T03:38:01.248Z",
    "impact_number": 0,
    "audit_number": 0,
    "audit_text": "",
    "tags": [
      "TechJobsForGood",
      "Mission Driven",
      "Tech"
    ],
    "ai_summary": "",
    "ai_red_flag_summary": "",
    "ai_score": 0,
    "ai_red_flag_score": 0,
    "ai_impact_summary": "",
    "ai_impact_score": 0
  },
  {
    "name": "Lead GIS Analyst NYC Office of Technology and Innovation New York, NY - $68K - $140K Data + Analytics Public Service &amp; Civic Engagement Partners &amp; Advocates Public Infrastructure We see technology as a tool for realizing Mayor de Blasio’s vision of making New York City the fairest big city in America. Technology can deliver inclusiveness, accessibility, and economic opportunity. We work to make this happen. Posted 4 weeks ago",
    "company_name": "Tech Jobs For Good",
    "location": "New York, NY",
    "remote": "Unknown",
    "location_lat": 40.7128,
    "location_lon": -74.006,
    "description": "",
    "type": "Unknown",
    "source": "TechJobsForGood",
    "source_url": "https://www.techjobsforgood.com/jobs/32677/?ref=homepage",
    "posted": "2026-05-26T03:38:01.248Z",
    "impact_number": 0,
    "audit_number": 0,
    "audit_text": "",
    "tags": [
      "TechJobsForGood",
      "Mission Driven",
      "Tech"
    ],
    "ai_summary": "",
    "ai_red_flag_summary": "",
    "ai_score": 0,
    "ai_red_flag_score": 0,
    "ai_impact_summary": "",
    "ai_impact_score": 0
  },
  {
    "name": "Specialist, Digital Accessibility Front Range Community College Westminster, CO - $61K - $64K Information Technology Front Range Community College is a higher education institution that offers a variety of college programs and educational services. Posted 4 weeks ago",
    "company_name": "Tech Jobs For Good",
    "location": "Westminster, CO",
    "remote": "Unknown",
    "location_lat": 38.627,
    "location_lon": -90.1994,
    "description": "",
    "type": "Unknown",
    "source": "TechJobsForGood",
    "source_url": "https://www.techjobsforgood.com/jobs/32671/?ref=homepage",
    "posted": "2026-05-26T03:38:01.248Z",
    "impact_number": 0,
    "audit_number": 0,
    "audit_text": "",
    "tags": [
      "TechJobsForGood",
      "Mission Driven",
      "Tech"
    ],
    "ai_summary": "",
    "ai_red_flag_summary": "",
    "ai_score": 0,
    "ai_red_flag_score": 0,
    "ai_impact_summary": "",
    "ai_impact_score": 0
  },
  {
    "name": "Staff AI Engineer – Agentic AI and Automaton Collective Health San Francisco, CA/Lehi, UT/Plano, TX - $160K - $250K Software Engineering Partners &amp; Advocates Health &amp; Well-Being Collective Health is on a mission to make it effortless for organizations and their people to understand, navigate and pay for their healthcare. Collective Health combines technology, design, and a human touch to allow benefits teams to deliver a truly enjoyable healthcare experience to their employees while also equipping benefits teams and their consulting partners with the data and insights necessary to help develop effective and efficient benefits strategies. Posted 4 days ago",
    "company_name": "Tech Jobs For Good",
    "location": "San Francisco, CA",
    "remote": "Unknown",
    "location_lat": 37.7749,
    "location_lon": -122.4194,
    "description": "",
    "type": "Unknown",
    "source": "TechJobsForGood",
    "source_url": "https://www.techjobsforgood.com/jobs/33260/?ref=homepage",
    "posted": "2026-05-26T03:38:01.248Z",
    "impact_number": 0,
    "audit_number": 0,
    "audit_text": "",
    "tags": [
      "TechJobsForGood",
      "Mission Driven",
      "Tech"
    ],
    "ai_summary": "",
    "ai_red_flag_summary": "",
    "ai_score": 0,
    "ai_red_flag_score": 0,
    "ai_impact_summary": "",
    "ai_impact_score": 0
  },
  {
    "name": "Lead Corporate Strategy Analyst Great Minds Boston, MA - $103K - $118K Data + Analytics Great Minds is an education company that specializes in curriculum development and educational resources. Posted 4 days ago",
    "company_name": "Tech Jobs For Good",
    "location": "Boston, MA",
    "remote": "Unknown",
    "location_lat": 42.3601,
    "location_lon": -71.0589,
    "description": "",
    "type": "Unknown",
    "source": "TechJobsForGood",
    "source_url": "https://www.techjobsforgood.com/jobs/33272/?ref=homepage",
    "posted": "2026-05-26T03:38:01.248Z",
    "impact_number": 0,
    "audit_number": 0,
    "audit_text": "",
    "tags": [
      "TechJobsForGood",
      "Mission Driven",
      "Tech"
    ],
    "ai_summary": "",
    "ai_red_flag_summary": "",
    "ai_score": 0,
    "ai_red_flag_score": 0,
    "ai_impact_summary": "",
    "ai_impact_score": 0
  },
  {
    "name": "Senior QA Engineer Butterfly Network New York, NY - $100K Software Engineering Health &amp; Well-Being Our mission is to democratize healthcare by making medical imaging accessible to everyone around the world. Posted 4 days ago",
    "company_name": "Tech Jobs For Good",
    "location": "New York, NY",
    "remote": "Unknown",
    "location_lat": 40.7128,
    "location_lon": -74.006,
    "description": "",
    "type": "Unknown",
    "source": "TechJobsForGood",
    "source_url": "https://www.techjobsforgood.com/jobs/33266/?ref=homepage",
    "posted": "2026-05-26T03:38:01.248Z",
    "impact_number": 0,
    "audit_number": 0,
    "audit_text": "",
    "tags": [
      "TechJobsForGood",
      "Mission Driven",
      "Tech"
    ],
    "ai_summary": "",
    "ai_red_flag_summary": "",
    "ai_score": 0,
    "ai_red_flag_score": 0,
    "ai_impact_summary": "",
    "ai_impact_score": 0
  },
  {
    "name": "Associate GIS Support Engineer NYC Office of Technology and Innovation New York, NY - $68K - $90K Information Technology Public Service &amp; Civic Engagement Partners &amp; Advocates Public Infrastructure We see technology as a tool for realizing Mayor de Blasio’s vision of making New York City the fairest big city in America. Technology can deliver inclusiveness, accessibility, and economic opportunity. We work to make this happen. Posted 4 weeks ago",
    "company_name": "Tech Jobs For Good",
    "location": "New York, NY",
    "remote": "Unknown",
    "location_lat": 40.7128,
    "location_lon": -74.006,
    "description": "",
    "type": "Unknown",
    "source": "TechJobsForGood",
    "source_url": "https://www.techjobsforgood.com/jobs/32675/?ref=homepage",
    "posted": "2026-05-26T03:38:01.248Z",
    "impact_number": 0,
    "audit_number": 0,
    "audit_text": "",
    "tags": [
      "TechJobsForGood",
      "Mission Driven",
      "Tech"
    ],
    "ai_summary": "",
    "ai_red_flag_summary": "",
    "ai_score": 0,
    "ai_red_flag_score": 0,
    "ai_impact_summary": "",
    "ai_impact_score": 0
  },
  {
    "name": "Engineering Manager (Data Platform &amp; Analytics Engineering) Kaluza London, Bristol, Edinburgh (UK) - $93K - $115K Information Technology Kaluza is an Energy Technology company that provides an Energy Intelligence Platform to help energy companies seamlessly coordinate their operations and facilitate the transition to a clean, electrified future. Posted 2 weeks ago",
    "company_name": "Tech Jobs For Good",
    "location": "Unknown",
    "remote": "Unknown",
    "location_lat": 26.4925331,
    "location_lon": 92.3308789,
    "description": "",
    "type": "Unknown",
    "source": "TechJobsForGood",
    "source_url": "https://www.techjobsforgood.com/jobs/33029/?ref=homepage",
    "posted": "2026-05-26T03:38:01.248Z",
    "impact_number": 0,
    "audit_number": 0,
    "audit_text": "",
    "tags": [
      "TechJobsForGood",
      "Mission Driven",
      "Tech"
    ],
    "ai_summary": "",
    "ai_red_flag_summary": "",
    "ai_score": 0,
    "ai_red_flag_score": 0,
    "ai_impact_summary": "",
    "ai_impact_score": 0
  },
  {
    "name": "Senior Cloud Release Engineer - Deployment &amp; Validation Systems Zipline South San Francisco, CA - $170K - $210K Information Technology Health &amp; Well-Being Global Peace &amp; Safety Climate Change We created Zipline to deliver medicine via drone to those who need it most Posted 1 week ago",
    "company_name": "Tech Jobs For Good",
    "location": "South San Francisco, CA",
    "remote": "Unknown",
    "location_lat": 50.9097,
    "location_lon": -1.4044,
    "description": "",
    "type": "Unknown",
    "source": "TechJobsForGood",
    "source_url": "https://www.techjobsforgood.com/jobs/33126/?ref=homepage",
    "posted": "2026-05-26T03:38:01.248Z",
    "impact_number": 0,
    "audit_number": 0,
    "audit_text": "",
    "tags": [
      "TechJobsForGood",
      "Mission Driven",
      "Tech"
    ],
    "ai_summary": "",
    "ai_red_flag_summary": "",
    "ai_score": 0,
    "ai_red_flag_score": 0,
    "ai_impact_summary": "",
    "ai_impact_score": 0
  },
  {
    "name": "Senior Software Engineer in Test (AI Agentic Systems) Collective Health Lehi, UT - $99K - $124K Software Engineering Partners &amp; Advocates Health &amp; Well-Being Collective Health is on a mission to make it effortless for organizations and their people to understand, navigate and pay for their healthcare. Collective Health combines technology, design, and a human touch to allow benefits teams to deliver a truly enjoyable healthcare experience to their employees while also equipping benefits teams and their consulting partners with the data and insights necessary to help develop effective and efficient benefits strategies. Posted 4 days ago",
    "company_name": "Tech Jobs For Good",
    "location": "Lehi, UT",
    "remote": "Unknown",
    "location_lat": 40.3881114,
    "location_lon": -111.8486019,
    "description": "",
    "type": "Unknown",
    "source": "TechJobsForGood",
    "source_url": "https://www.techjobsforgood.com/jobs/33259/?ref=homepage",
    "posted": "2026-05-26T03:38:01.248Z",
    "impact_number": 0,
    "audit_number": 0,
    "audit_text": "",
    "tags": [
      "TechJobsForGood",
      "Mission Driven",
      "Tech"
    ],
    "ai_summary": "",
    "ai_red_flag_summary": "",
    "ai_score": 0,
    "ai_red_flag_score": 0,
    "ai_impact_summary": "",
    "ai_impact_score": 0
  },
  {
    "name": "GIS Support Engineer NYC Office of Technology and Innovation New York, NY - $68K - $120K Information Technology Public Service &amp; Civic Engagement Partners &amp; Advocates Public Infrastructure We see technology as a tool for realizing Mayor de Blasio’s vision of making New York City the fairest big city in America. Technology can deliver inclusiveness, accessibility, and economic opportunity. We work to make this happen. Posted 4 weeks ago",
    "company_name": "Tech Jobs For Good",
    "location": "New York, NY",
    "remote": "Unknown",
    "location_lat": 40.7128,
    "location_lon": -74.006,
    "description": "",
    "type": "Unknown",
    "source": "TechJobsForGood",
    "source_url": "https://www.techjobsforgood.com/jobs/32678/?ref=homepage",
    "posted": "2026-05-26T03:38:01.248Z",
    "impact_number": 0,
    "audit_number": 0,
    "audit_text": "",
    "tags": [
      "TechJobsForGood",
      "Mission Driven",
      "Tech"
    ],
    "ai_summary": "",
    "ai_red_flag_summary": "",
    "ai_score": 0,
    "ai_red_flag_score": 0,
    "ai_impact_summary": "",
    "ai_impact_score": 0
  },
  {
    "name": "Digital Design Technician Toronto Public Library Toronto (CAN) - Can$61K - Can$69K Information Technology Toronto Public Library is a public library that provides educational resources, information services, and promotes literature within the community. Posted 4 weeks ago",
    "company_name": "Tech Jobs For Good",
    "location": "Unknown",
    "remote": "Unknown",
    "location_lat": 26.4925331,
    "location_lon": 92.3308789,
    "description": "",
    "type": "Unknown",
    "source": "TechJobsForGood",
    "source_url": "https://www.techjobsforgood.com/jobs/32688/?ref=homepage",
    "posted": "2026-05-26T03:38:01.248Z",
    "impact_number": 0,
    "audit_number": 0,
    "audit_text": "",
    "tags": [
      "TechJobsForGood",
      "Mission Driven",
      "Tech"
    ],
    "ai_summary": "",
    "ai_red_flag_summary": "",
    "ai_score": 0,
    "ai_red_flag_score": 0,
    "ai_impact_summary": "",
    "ai_impact_score": 0
  },
  {
    "name": "Senior Network Systems Engineer (San Jose, CA) Electric Hydrogen San Jose, CA - $155K - $182K Software Engineering Clean Energy Climate Change Our mission is to create an abundant and decarbonized material future. Our goal is to deliver hydrogen from renewable electrolysis for heavy industry, at prices below fossil fuels. Posted 2 weeks ago",
    "company_name": "Tech Jobs For Good",
    "location": "San Jose, CA",
    "remote": "Unknown",
    "location_lat": 37.3382,
    "location_lon": -121.8863,
    "description": "",
    "type": "Unknown",
    "source": "TechJobsForGood",
    "source_url": "https://www.techjobsforgood.com/jobs/32966/?ref=homepage",
    "posted": "2026-05-26T03:38:01.248Z",
    "impact_number": 0,
    "audit_number": 0,
    "audit_text": "",
    "tags": [
      "TechJobsForGood",
      "Mission Driven",
      "Tech"
    ],
    "ai_summary": "",
    "ai_red_flag_summary": "",
    "ai_score": 0,
    "ai_red_flag_score": 0,
    "ai_impact_summary": "",
    "ai_impact_score": 0
  },
  {
    "name": "Manager, Information Technology Services Front Range Community College Fort Collins, CO - $62K - $66K Information Technology Front Range Community College is a higher education institution that offers a variety of college programs and educational services. Posted 4 weeks ago",
    "company_name": "Tech Jobs For Good",
    "location": "Fort Collins, CO",
    "remote": "Unknown",
    "location_lat": 32.7555,
    "location_lon": -97.3308,
    "description": "",
    "type": "Unknown",
    "source": "TechJobsForGood",
    "source_url": "https://www.techjobsforgood.com/jobs/32670/?ref=homepage",
    "posted": "2026-05-26T03:38:01.248Z",
    "impact_number": 0,
    "audit_number": 0,
    "audit_text": "",
    "tags": [
      "TechJobsForGood",
      "Mission Driven",
      "Tech"
    ],
    "ai_summary": "",
    "ai_red_flag_summary": "",
    "ai_score": 0,
    "ai_red_flag_score": 0,
    "ai_impact_summary": "",
    "ai_impact_score": 0
  },
  {
    "name": "Senior Network Systems Engineer (Devens, MA) Electric Hydrogen Devens, MA - $135K - $160K Software Engineering Clean Energy Climate Change Our mission is to create an abundant and decarbonized material future. Our goal is to deliver hydrogen from renewable electrolysis for heavy industry, at prices below fossil fuels. Posted 2 weeks ago",
    "company_name": "Tech Jobs For Good",
    "location": "Devens, MA",
    "remote": "Unknown",
    "location_lat": 42.5175,
    "location_lon": -71.6397,
    "description": "",
    "type": "Unknown",
    "source": "TechJobsForGood",
    "source_url": "https://www.techjobsforgood.com/jobs/32965/?ref=homepage",
    "posted": "2026-05-26T03:38:01.248Z",
    "impact_number": 0,
    "audit_number": 0,
    "audit_text": "",
    "tags": [
      "TechJobsForGood",
      "Mission Driven",
      "Tech"
    ],
    "ai_summary": "",
    "ai_red_flag_summary": "",
    "ai_score": 0,
    "ai_red_flag_score": 0,
    "ai_impact_summary": "",
    "ai_impact_score": 0
  },
  {
    "name": "ITS Lead, Digital Enablement Toronto Public Library Toronto (CAN) - Can$97K - Can$110K Information Technology Toronto Public Library is a public library that provides educational resources, information services, and promotes literature within the community. Posted 4 weeks ago",
    "company_name": "Tech Jobs For Good",
    "location": "Unknown",
    "remote": "Unknown",
    "location_lat": 26.4925331,
    "location_lon": 92.3308789,
    "description": "",
    "type": "Unknown",
    "source": "TechJobsForGood",
    "source_url": "https://www.techjobsforgood.com/jobs/32687/?ref=homepage",
    "posted": "2026-05-26T03:38:01.248Z",
    "impact_number": 0,
    "audit_number": 0,
    "audit_text": "",
    "tags": [
      "TechJobsForGood",
      "Mission Driven",
      "Tech"
    ],
    "ai_summary": "",
    "ai_red_flag_summary": "",
    "ai_score": 0,
    "ai_red_flag_score": 0,
    "ai_impact_summary": "",
    "ai_impact_score": 0
  },
  {
    "name": "Deputy Commissioner and Chief Information Security Officer NYC Office of Technology and Innovation Brooklyn, NY - $124K - $270K Information Technology Public Service &amp; Civic Engagement Partners &amp; Advocates Public Infrastructure We see technology as a tool for realizing Mayor de Blasio’s vision of making New York City the fairest big city in America. Technology can deliver inclusiveness, accessibility, and economic opportunity. We work to make this happen. Posted 4 weeks ago",
    "company_name": "Tech Jobs For Good",
    "location": "Unknown",
    "remote": "Unknown",
    "location_lat": 26.4925331,
    "location_lon": 92.3308789,
    "description": "",
    "type": "Unknown",
    "source": "TechJobsForGood",
    "source_url": "https://www.techjobsforgood.com/jobs/32673/?ref=homepage",
    "posted": "2026-05-26T03:38:01.248Z",
    "impact_number": 0,
    "audit_number": 0,
    "audit_text": "",
    "tags": [
      "TechJobsForGood",
      "Mission Driven",
      "Tech"
    ],
    "ai_summary": "",
    "ai_red_flag_summary": "",
    "ai_score": 0,
    "ai_red_flag_score": 0,
    "ai_impact_summary": "",
    "ai_impact_score": 0
  },
  {
    "name": "Graphic Designer Toronto Public Library Toronto (CAN) - Can$0K - Can$0K Information Technology Toronto Public Library is a public library that provides educational resources, information services, and promotes literature within the community. Posted 4 weeks ago",
    "company_name": "Tech Jobs For Good",
    "location": "Unknown",
    "remote": "Unknown",
    "location_lat": 26.4925331,
    "location_lon": 92.3308789,
    "description": "",
    "type": "Unknown",
    "source": "TechJobsForGood",
    "source_url": "https://www.techjobsforgood.com/jobs/32689/?ref=homepage",
    "posted": "2026-05-26T03:38:01.248Z",
    "impact_number": 0,
    "audit_number": 0,
    "audit_text": "",
    "tags": [
      "TechJobsForGood",
      "Mission Driven",
      "Tech"
    ],
    "ai_summary": "",
    "ai_red_flag_summary": "",
    "ai_score": 0,
    "ai_red_flag_score": 0,
    "ai_impact_summary": "",
    "ai_impact_score": 0
  }
]